clipsmith/__init__.py
clipsmith/_ffmpeg.py
clipsmith/cli/main.py
clipsmith/clip/__init__.py
clipsmith/clip/clip.py
clipsmith/clip/operation.py
clipsmith/context.py
clipsmith/profile.py
clipsmith/profiles.py
clipsmith/video/__init__.py
clipsmith/video/base.py
clipsmith/video/raw.py
clipsmith-0.2.1.dist-info/LICENSE
clipsmith-0.2.1.dist-info/METADATA
clipsmith-0.2.1.dist-info/WHEEL
clipsmith-0.2.1.dist-info/entry_points.txt
clipsmith-0.2.1.dist-info/RECORD
