Metadata-Version: 2.3
Name: clipsmith
Version: 0.2.1
Summary: Utility to work with video clips, especially suited for creating timelapses from dashcam footage
Author: mm21
Author-email: mm21.dev@gmail.com
Requires-Python: >=3.11,<4.0
Classifier: Programming Language :: Python :: Implementation :: CPython
Classifier: Operating System :: OS Independent
Classifier: Typing :: Typed
Classifier: Topic :: Software Development :: Libraries :: Python Modules
Classifier: Development Status :: 4 - Beta
Classifier: Natural Language :: English
Classifier: License :: OSI Approved :: MIT License
Classifier: Programming Language :: Python :: 3
Classifier: Programming Language :: Python :: 3.11
Classifier: Programming Language :: Python :: 3.12
Classifier: Programming Language :: Python :: 3.13
Requires-Dist: doit (>=0.36.0,<0.37.0)
Requires-Dist: pydantic (>=2.10.2,<3.0.0)
Requires-Dist: pyrollup (>=0.1.0,<0.2.0)
Requires-Dist: pyyaml (>=6.0.2,<7.0.0)
Requires-Dist: typer (>=0.15.0,<0.16.0)
Project-URL: Homepage, https://github.com/mm21/clipsmith
